ap_features/__init__.py
ap_features/_numba.py
ap_features/average.py
ap_features/background.py
ap_features/beat.py
ap_features/chopping.py
ap_features/features.py
ap_features/filters.py
ap_features/plot.py
ap_features/testing.py
ap_features/utils.py
ap_features-2026.1.0.dist-info/licenses/AUTHORS.md
ap_features-2026.1.0.dist-info/licenses/LICENSE
ap_features-2026.1.0.dist-info/METADATA
ap_features-2026.1.0.dist-info/WHEEL
ap_features-2026.1.0.dist-info/top_level.txt
ap_features-2026.1.0.dist-info/RECORD
