Metadata-Version: 2.4
Name: ap_features
Version: 2026.1.0
Summary: Package to compute features of traces from action potential models
Author-email: Henrik Finsberg <henriknf@simula.no>, "Kristian G. Hustad" <kghustad@simula.no>
License: LGPL-2.1
Project-URL: Homepage, https://computationalphysiology.github.io/ap_features
Project-URL: Documentation, https://computationalphysiology.github.io/ap_features
Project-URL: Source, https://github.com/ComputationalPhysiology/ap_features
Project-URL: Tracker, https://github.com/ComputationalPhysiology/ap_features/issues
Keywords: action potential,cell,models,features
Requires-Python: >=3.7
License-File: LICENSE
License-File: AUTHORS.md
Requires-Dist: numpy
Requires-Dist: scipy
Requires-Dist: tqdm
Provides-Extra: numba
Requires-Dist: numba; extra == "numba"
Provides-Extra: array
Requires-Dist: h5py; extra == "array"
Requires-Dist: dask[array]; extra == "array"
Requires-Dist: numba; extra == "array"
Provides-Extra: dev
Requires-Dist: pdbpp; extra == "dev"
Requires-Dist: ipython; extra == "dev"
Requires-Dist: bump2version; extra == "dev"
Requires-Dist: pre-commit; extra == "dev"
Provides-Extra: plot
Requires-Dist: matplotlib; extra == "plot"
Provides-Extra: pypi
Requires-Dist: twine; extra == "pypi"
Requires-Dist: build; extra == "pypi"
Provides-Extra: docs
Requires-Dist: sphinx; extra == "docs"
Requires-Dist: sphinx-togglebutton; extra == "docs"
Requires-Dist: myst-nb; extra == "docs"
Requires-Dist: myst-parser; extra == "docs"
Requires-Dist: sphinx-copybutton; extra == "docs"
Requires-Dist: sphinx-design; extra == "docs"
Requires-Dist: sphinx-book-theme; extra == "docs"
Requires-Dist: linkify-it-py; extra == "docs"
Requires-Dist: sphinx-multitoc-numbering; extra == "docs"
Requires-Dist: sphinx-comments; extra == "docs"
Requires-Dist: sphinx-external-toc; extra == "docs"
Requires-Dist: sphinx-thebe; extra == "docs"
Requires-Dist: ap_features[plot]; extra == "docs"
Requires-Dist: numba; extra == "docs"
Provides-Extra: test
Requires-Dist: pytest; extra == "test"
Requires-Dist: pytest-cov; extra == "test"
Requires-Dist: ap_features[array]; extra == "test"
Provides-Extra: all
Requires-Dist: ap_features[test]; extra == "all"
Requires-Dist: ap_features[docs]; extra == "all"
Requires-Dist: ap_features[pypi]; extra == "all"
Requires-Dist: ap_features[dev]; extra == "all"
Requires-Dist: ap_features[array]; extra == "all"
Requires-Dist: ap_features[plot]; extra == "all"
Dynamic: license-file
